{"cameraMode":{"drawMode":0,"name":"Shaded","section":"Shading Mode"},"sceneLighting":true,"audioPlay":false,"sceneViewState":{"m_AlwaysRefresh":false,"showFog":true,"showSkybox":false,"showFlares":true,"showImageEffects":true,"showParticleSystems":true,"showVisualEffectGraphs":true,"m_FxEnabled":true},"in2DMode":false,"pivot":{"x":0.0,"y":-0.042598724365234378,"z":1.8480110168457032},"rotation":{"x":0.03299399092793465,"y":-0.0014991930220276118,"z":0.00005055579822510481,"w":0.999455988407135},"size":60.911827087402347,"orthographic":false}